<annotation>
	<folder>dataset</folder>
	<filename>img-658.jpg</filename>
	<path>/CSE-800/Thesis/2020-01-23/dataset/img-658.jpg</path>
	<source>
		<database>Unknown</database>
	</source>
	<size>
		<width>300</width>
		<height>400</height>
		<depth>3</depth>
	</size>
	<segmented>0</segmented>
	<object>
		<name>pothole</name>
		<pose>Unspecified</pose>
		<truncated>0</truncated>
		<difficult>0</difficult>
		<bndbox>
			<xmin>224</xmin>
			<ymin>175</ymin>
			<xmax>283</xmax>
			<ymax>226</ymax>
		</bndbox>
	</object>
	<object>
		<name>pothole</name>
		<pose>Unspecified</pose>
		<truncated>0</truncated>
		<difficult>0</difficult>
		<bndbox>
			<xmin>88</xmin>
			<ymin>168</ymin>
			<xmax>130</xmax>
			<ymax>188</ymax>
		</bndbox>
	</object>
	<object>
		<name>pothole</name>
		<pose>Unspecified</pose>
		<truncated>0</truncated>
		<difficult>0</difficult>
		<bndbox>
			<xmin>66</xmin>
			<ymin>240</ymin>
			<xmax>229</xmax>
			<ymax>314</ymax>
		</bndbox>
	</object>
	<object>
		<name>pothole</name>
		<pose>Unspecified</pose>
		<truncated>0</truncated>
		<difficult>0</difficult>
		<bndbox>
			<xmin>136</xmin>
			<ymin>63</ymin>
			<xmax>182</xmax>
			<ymax>82</ymax>
		</bndbox>
	</object>
</annotation>