<annotation>
	<folder>dataset</folder>
	<filename>img-617.jpg</filename>
	<path>/CSE-800/Thesis/2020-01-23/dataset/img-617.jpg</path>
	<source>
		<database>Unknown</database>
	</source>
	<size>
		<width>450</width>
		<height>300</height>
		<depth>3</depth>
	</size>
	<segmented>0</segmented>
	<object>
		<name>pothole</name>
		<pose>Unspecified</pose>
		<truncated>0</truncated>
		<difficult>0</difficult>
		<bndbox>
			<xmin>210</xmin>
			<ymin>207</ymin>
			<xmax>272</xmax>
			<ymax>223</ymax>
		</bndbox>
	</object>
	<object>
		<name>pothole</name>
		<pose>Unspecified</pose>
		<truncated>0</truncated>
		<difficult>0</difficult>
		<bndbox>
			<xmin>249</xmin>
			<ymin>207</ymin>
			<xmax>285</xmax>
			<ymax>243</ymax>
		</bndbox>
	</object>
	<object>
		<name>pothole</name>
		<pose>Unspecified</pose>
		<truncated>0</truncated>
		<difficult>0</difficult>
		<bndbox>
			<xmin>84</xmin>
			<ymin>245</ymin>
			<xmax>287</xmax>
			<ymax>297</ymax>
		</bndbox>
	</object>
	<object>
		<name>pothole</name>
		<pose>Unspecified</pose>
		<truncated>0</truncated>
		<difficult>0</difficult>
		<bndbox>
			<xmin>174</xmin>
			<ymin>186</ymin>
			<xmax>209</xmax>
			<ymax>198</ymax>
		</bndbox>
	</object>
	<object>
		<name>pothole</name>
		<pose>Unspecified</pose>
		<truncated>0</truncated>
		<difficult>0</difficult>
		<bndbox>
			<xmin>166</xmin>
			<ymin>169</ymin>
			<xmax>214</xmax>
			<ymax>176</ymax>
		</bndbox>
	</object>
</annotation>