<annotation>
	<folder></folder>
	<filename>raccoon-117_jpg.rf.b52f222361393ee05f2ba49b5b7f9924.jpg</filename>
	<path>raccoon-117_jpg.rf.b52f222361393ee05f2ba49b5b7f9924.jpg</path>
	<source>
		<database>roboflow.ai</database>
	</source>
	<size>
		<width>640</width>
		<height>448</height>
		<depth>3</depth>
	</size>
	<segmented>0</segmented>
	<object>
		<name>raccoon</name>
		<pose>Unspecified</pose>
		<truncated>0</truncated>
		<difficult>0</difficult>
		<occluded>0</occluded>
		<bndbox>
			<xmin>101</xmin>
			<xmax>267</xmax>
			<ymin>125</ymin>
			<ymax>325</ymax>
		</bndbox>
	</object>
	<object>
		<name>raccoon</name>
		<pose>Unspecified</pose>
		<truncated>0</truncated>
		<difficult>0</difficult>
		<occluded>0</occluded>
		<bndbox>
			<xmin>343</xmin>
			<xmax>571</xmax>
			<ymin>102</ymin>
			<ymax>298</ymax>
		</bndbox>
	</object>
</annotation>
